{
  "Experiment": "Localization Experiment.",
  "SubjectInformation": {
    "Subject": "HP_Static",
    "Age": 23,
    "Gender": "male"
  },
  "StartTime": "6 Mar 2025 14:08:39",
  "EndTime": "6 Mar 2025 14:24:23",
  "Results": {
    "PresentedOrderOfParts": [
      1,
      0,
      2
    ],
    "Parts": [
      {
        "PresentedOrderOfTrials": [
          0,
          10,
          9,
          11,
          7,
          3,
          8,
          1,
          5,
          4,
          2,
          6
        ],
        "Trials": [
          {
            "TrialName": "1LS_BB",
            "Ratings": [
              50.0,
              0.0,
              0.0,
              0.0,
              0.0,
              0.0,
              0.0,
              0.0,
              1.0,
              0.0,
              0.0,
              0.0,
              0.0,
              0.0,
              0.0,
              0.0
            ],
            "Scale": {
              "Min": 0.0,
              "Max": 100.0,
              "StepSize": 1.0,
              "DefaultValue": 50.0,
              "Labels": [
                "",
                "",
                "",
                "",
                ""
              ]
            },
            "PresentedOrderOfStimuli": [
              0
            ],
            "ElapsedTimeInSeconds": 4.6468018
          },
          {
            "TrialName": "2LS_15DEG_BB",
            "Ratings": [
              50.0,
              0.0,
              0.0,
              0.0,
              0.0,
              0.0,
              0.0,
              1.0,
              0.0,
              1.0,
              0.0,
              0.0,
              0.0,
              0.0,
              0.0,
              0.0
            ],
            "Scale": {
              "Min": 0.0,
              "Max": 100.0,
              "StepSize": 1.0,
              "DefaultValue": 50.0,
              "Labels": [
                "",
                "",
                "",
                "",
                ""
              ]
            },
            "PresentedOrderOfStimuli": [
              0
            ],
            "ElapsedTimeInSeconds": 7.1439445
          },
          {
            "TrialName": "2LS_30DEG_BB",
            "Ratings": [
              50.0,
              0.0,
              0.0,
              0.0,
              0.0,
              0.0,
              0.0,
              1.0,
              1.0,
              1.0,
              0.0,
              0.0,
              0.0,
              0.0,
              0.0,
              0.0
            ],
            "Scale": {
              "Min": 0.0,
              "Max": 100.0,
              "StepSize": 1.0,
              "DefaultValue": 50.0,
              "Labels": [
                "",
                "",
                "",
                "",
                ""
              ]
            },
            "PresentedOrderOfStimuli": [
              0
            ],
            "ElapsedTimeInSeconds": 5.091790899999999
          },
          {
            "TrialName": "2LS_45DEG_BB",
            "Ratings": [
              50.0,
              0.0,
              0.0,
              0.0,
              0.0,
              1.0,
              0.0,
              0.0,
              0.0,
              0.0,
              0.0,
              1.0,
              0.0,
              0.0,
              0.0,
              0.0
            ],
            "Scale": {
              "Min": 0.0,
              "Max": 100.0,
              "StepSize": 1.0,
              "DefaultValue": 50.0,
              "Labels": [
                "",
                "",
                "",
                "",
                ""
              ]
            },
            "PresentedOrderOfStimuli": [
              0
            ],
            "ElapsedTimeInSeconds": 8.161853199999999
          },
          {
            "TrialName": "2LS_60DEG_BB",
            "Ratings": [
              50.0,
              0.0,
              0.0,
              1.0,
              0.0,
              0.0,
              0.0,
              0.0,
              0.0,
              0.0,
              0.0,
              0.0,
              0.0,
              1.0,
              0.0,
              0.0
            ],
            "Scale": {
              "Min": 0.0,
              "Max": 100.0,
              "StepSize": 1.0,
              "DefaultValue": 50.0,
              "Labels": [
                "",
                "",
                "",
                "",
                ""
              ]
            },
            "PresentedOrderOfStimuli": [
              0
            ],
            "ElapsedTimeInSeconds": 27.0572247
          },
          {
            "TrialName": "2LS_90DEG_BB",
            "Ratings": [
              50.0,
              1.0,
              0.0,
              0.0,
              0.0,
              0.0,
              0.0,
              0.0,
              0.0,
              0.0,
              0.0,
              0.0,
              0.0,
              0.0,
              0.0,
              1.0
            ],
            "Scale": {
              "Min": 0.0,
              "Max": 100.0,
              "StepSize": 1.0,
              "DefaultValue": 50.0,
              "Labels": [
                "",
                "",
                "",
                "",
                ""
              ]
            },
            "PresentedOrderOfStimuli": [
              0
            ],
            "ElapsedTimeInSeconds": 13.6608332
          },
          {
            "TrialName": "3LS_15DEG_BB",
            "Ratings": [
              50.0,
              0.0,
              0.0,
              0.0,
              0.0,
              0.0,
              0.0,
              1.0,
              0.0,
              1.0,
              0.0,
              0.0,
              0.0,
              0.0,
              0.0,
              0.0
            ],
            "Scale": {
              "Min": 0.0,
              "Max": 100.0,
              "StepSize": 1.0,
              "DefaultValue": 50.0,
              "Labels": [
                "",
                "",
                "",
                "",
                ""
              ]
            },
            "PresentedOrderOfStimuli": [
              0
            ],
            "ElapsedTimeInSeconds": 20.5701503
          },
          {
            "TrialName": "3LS_30DEG_BB",
            "Ratings": [
              50.0,
              0.0,
              0.0,
              0.0,
              0.0,
              0.0,
              1.0,
              0.0,
              1.0,
              0.0,
              1.0,
              0.0,
              0.0,
              0.0,
              0.0,
              0.0
            ],
            "Scale": {
              "Min": 0.0,
              "Max": 100.0,
              "StepSize": 1.0,
              "DefaultValue": 50.0,
              "Labels": [
                "",
                "",
                "",
                "",
                ""
              ]
            },
            "PresentedOrderOfStimuli": [
              0
            ],
            "ElapsedTimeInSeconds": 10.6001359
          },
          {
            "TrialName": "3LS_45DEG_BB",
            "Ratings": [
              50.0,
              0.0,
              0.0,
              0.0,
              0.0,
              1.0,
              0.0,
              0.0,
              1.0,
              0.0,
              0.0,
              1.0,
              0.0,
              0.0,
              0.0,
              0.0
            ],
            "Scale": {
              "Min": 0.0,
              "Max": 100.0,
              "StepSize": 1.0,
              "DefaultValue": 50.0,
              "Labels": [
                "",
                "",
                "",
                "",
                ""
              ]
            },
            "PresentedOrderOfStimuli": [
              0
            ],
            "ElapsedTimeInSeconds": 35.1284635
          },
          {
            "TrialName": "3LS_60DEG_BB",
            "Ratings": [
              50.0,
              0.0,
              0.0,
              0.0,
              1.0,
              0.0,
              0.0,
              0.0,
              1.0,
              0.0,
              0.0,
              0.0,
              1.0,
              0.0,
              0.0,
              0.0
            ],
            "Scale": {
              "Min": 0.0,
              "Max": 100.0,
              "StepSize": 1.0,
              "DefaultValue": 50.0,
              "Labels": [
                "",
                "",
                "",
                "",
                ""
              ]
            },
            "PresentedOrderOfStimuli": [
              0
            ],
            "ElapsedTimeInSeconds": 18.3273704
          },
          {
            "TrialName": "3LS_90DEG_BB",
            "Ratings": [
              50.0,
              0.0,
              1.0,
              0.0,
              0.0,
              0.0,
              0.0,
              0.0,
              1.0,
              0.0,
              0.0,
              0.0,
              0.0,
              0.0,
              1.0,
              0.0
            ],
            "Scale": {
              "Min": 0.0,
              "Max": 100.0,
              "StepSize": 1.0,
              "DefaultValue": 50.0,
              "Labels": [
                "",
                "",
                "",
                "",
                ""
              ]
            },
            "PresentedOrderOfStimuli": [
              0
            ],
            "ElapsedTimeInSeconds": 45.42431149999999
          },
          {
            "TrialName": "13LS_90DEG_BB",
            "Ratings": [
              50.0,
              0.0,
              0.0,
              1.0,
              0.0,
              0.0,
              0.0,
              0.0,
              1.0,
              0.0,
              0.0,
              0.0,
              0.0,
              1.0,
              0.0,
              0.0
            ],
            "Scale": {
              "Min": 0.0,
              "Max": 100.0,
              "StepSize": 1.0,
              "DefaultValue": 50.0,
              "Labels": [
                "",
                "",
                "",
                "",
                ""
              ]
            },
            "PresentedOrderOfStimuli": [
              0
            ],
            "ElapsedTimeInSeconds": 11.3182576
          }
        ]
      },
      {
        "PresentedOrderOfTrials": [
          0,
          7,
          11,
          6,
          8,
          2,
          1,
          4,
          10,
          5,
          3,
          9
        ],
        "Trials": [
          {
            "TrialName": "1LS_LP",
            "Ratings": [
              50.0,
              0.0,
              0.0,
              0.0,
              0.0,
              0.0,
              0.0,
              0.0,
              1.0,
              0.0,
              0.0,
              0.0,
              0.0,
              0.0,
              0.0,
              0.0
            ],
            "Scale": {
              "Min": 0.0,
              "Max": 100.0,
              "StepSize": 1.0,
              "DefaultValue": 50.0,
              "Labels": [
                "",
                "",
                "",
                "",
                ""
              ]
            },
            "PresentedOrderOfStimuli": [
              0
            ],
            "ElapsedTimeInSeconds": 29.870436
          },
          {
            "TrialName": "2LS_15DEG_LP",
            "Ratings": [
              50.0,
              0.0,
              0.0,
              0.0,
              0.0,
              0.0,
              1.0,
              0.0,
              1.0,
              0.0,
              1.0,
              0.0,
              0.0,
              0.0,
              0.0,
              0.0
            ],
            "Scale": {
              "Min": 0.0,
              "Max": 100.0,
              "StepSize": 1.0,
              "DefaultValue": 50.0,
              "Labels": [
                "",
                "",
                "",
                "",
                ""
              ]
            },
            "PresentedOrderOfStimuli": [
              0
            ],
            "ElapsedTimeInSeconds": 26.5036432
          },
          {
            "TrialName": "2LS_30DEG_LP",
            "Ratings": [
              50.0,
              0.0,
              0.0,
              0.0,
              1.0,
              0.0,
              0.0,
              0.0,
              1.0,
              0.0,
              0.0,
              0.0,
              1.0,
              0.0,
              0.0,
              0.0
            ],
            "Scale": {
              "Min": 0.0,
              "Max": 100.0,
              "StepSize": 1.0,
              "DefaultValue": 50.0,
              "Labels": [
                "",
                "",
                "",
                "",
                ""
              ]
            },
            "PresentedOrderOfStimuli": [
              0
            ],
            "ElapsedTimeInSeconds": 15.8962041
          },
          {
            "TrialName": "2LS_45DEG_LP",
            "Ratings": [
              50.0,
              0.0,
              0.0,
              0.0,
              1.0,
              0.0,
              0.0,
              0.0,
              1.0,
              0.0,
              0.0,
              0.0,
              1.0,
              0.0,
              0.0,
              0.0
            ],
            "Scale": {
              "Min": 0.0,
              "Max": 100.0,
              "StepSize": 1.0,
              "DefaultValue": 50.0,
              "Labels": [
                "",
                "",
                "",
                "",
                ""
              ]
            },
            "PresentedOrderOfStimuli": [
              0
            ],
            "ElapsedTimeInSeconds": 104.1579522
          },
          {
            "TrialName": "2LS_60DEG_LP",
            "Ratings": [
              50.0,
              1.0,
              0.0,
              0.0,
              0.0,
              0.0,
              0.0,
              0.0,
              0.0,
              0.0,
              0.0,
              0.0,
              0.0,
              0.0,
              0.0,
              1.0
            ],
            "Scale": {
              "Min": 0.0,
              "Max": 100.0,
              "StepSize": 1.0,
              "DefaultValue": 50.0,
              "Labels": [
                "",
                "",
                "",
                "",
                ""
              ]
            },
            "PresentedOrderOfStimuli": [
              0
            ],
            "ElapsedTimeInSeconds": 21.1475351
          },
          {
            "TrialName": "2LS_90DEG_LP",
            "Ratings": [
              50.0,
              0.0,
              0.0,
              1.0,
              0.0,
              0.0,
              0.0,
              0.0,
              0.0,
              0.0,
              0.0,
              0.0,
              0.0,
              1.0,
              0.0,
              0.0
            ],
            "Scale": {
              "Min": 0.0,
              "Max": 100.0,
              "StepSize": 1.0,
              "DefaultValue": 50.0,
              "Labels": [
                "",
                "",
                "",
                "",
                ""
              ]
            },
            "PresentedOrderOfStimuli": [
              0
            ],
            "ElapsedTimeInSeconds": 159.6842687
          },
          {
            "TrialName": "3LS_15DEG_LP",
            "Ratings": [
              50.0,
              0.0,
              0.0,
              0.0,
              0.0,
              0.0,
              0.0,
              1.0,
              0.0,
              1.0,
              0.0,
              0.0,
              0.0,
              0.0,
              0.0,
              0.0
            ],
            "Scale": {
              "Min": 0.0,
              "Max": 100.0,
              "StepSize": 1.0,
              "DefaultValue": 50.0,
              "Labels": [
                "",
                "",
                "",
                "",
                ""
              ]
            },
            "PresentedOrderOfStimuli": [
              0
            ],
            "ElapsedTimeInSeconds": 16.2900473
          },
          {
            "TrialName": "3LS_30DEG_LP",
            "Ratings": [
              50.0,
              0.0,
              0.0,
              0.0,
              1.0,
              0.0,
              0.0,
              0.0,
              0.0,
              0.0,
              0.0,
              0.0,
              1.0,
              0.0,
              0.0,
              0.0
            ],
            "Scale": {
              "Min": 0.0,
              "Max": 100.0,
              "StepSize": 1.0,
              "DefaultValue": 50.0,
              "Labels": [
                "",
                "",
                "",
                "",
                ""
              ]
            },
            "PresentedOrderOfStimuli": [
              0
            ],
            "ElapsedTimeInSeconds": 44.84806
          },
          {
            "TrialName": "3LS_45DEG_LP",
            "Ratings": [
              50.0,
              0.0,
              0.0,
              1.0,
              0.0,
              0.0,
              0.0,
              0.0,
              0.0,
              0.0,
              0.0,
              0.0,
              0.0,
              1.0,
              0.0,
              0.0
            ],
            "Scale": {
              "Min": 0.0,
              "Max": 100.0,
              "StepSize": 1.0,
              "DefaultValue": 50.0,
              "Labels": [
                "",
                "",
                "",
                "",
                ""
              ]
            },
            "PresentedOrderOfStimuli": [
              0
            ],
            "ElapsedTimeInSeconds": 12.6480276
          },
          {
            "TrialName": "3LS_60DEG_LP",
            "Ratings": [
              50.0,
              0.0,
              0.0,
              0.0,
              0.0,
              1.0,
              0.0,
              0.0,
              1.0,
              0.0,
              0.0,
              1.0,
              0.0,
              0.0,
              0.0,
              0.0
            ],
            "Scale": {
              "Min": 0.0,
              "Max": 100.0,
              "StepSize": 1.0,
              "DefaultValue": 50.0,
              "Labels": [
                "",
                "",
                "",
                "",
                ""
              ]
            },
            "PresentedOrderOfStimuli": [
              0
            ],
            "ElapsedTimeInSeconds": 9.4071923
          },
          {
            "TrialName": "3LS_90DEG_LP",
            "Ratings": [
              50.0,
              0.0,
              1.0,
              0.0,
              0.0,
              0.0,
              0.0,
              0.0,
              1.0,
              0.0,
              0.0,
              0.0,
              0.0,
              0.0,
              1.0,
              0.0
            ],
            "Scale": {
              "Min": 0.0,
              "Max": 100.0,
              "StepSize": 1.0,
              "DefaultValue": 50.0,
              "Labels": [
                "",
                "",
                "",
                "",
                ""
              ]
            },
            "PresentedOrderOfStimuli": [
              0
            ],
            "ElapsedTimeInSeconds": 6.037833099999999
          },
          {
            "TrialName": "13LS_90DEG_LP",
            "Ratings": [
              50.0,
              0.0,
              1.0,
              0.0,
              0.0,
              0.0,
              0.0,
              0.0,
              0.0,
              0.0,
              0.0,
              0.0,
              0.0,
              0.0,
              1.0,
              0.0
            ],
            "Scale": {
              "Min": 0.0,
              "Max": 100.0,
              "StepSize": 1.0,
              "DefaultValue": 50.0,
              "Labels": [
                "",
                "",
                "",
                "",
                ""
              ]
            },
            "PresentedOrderOfStimuli": [
              0
            ],
            "ElapsedTimeInSeconds": 21.3737042
          }
        ]
      },
      {
        "PresentedOrderOfTrials": [
          0,
          5,
          1,
          3,
          9,
          2,
          11,
          10,
          4,
          8,
          7,
          6
        ],
        "Trials": [
          {
            "TrialName": "1LS_HP",
            "Ratings": [
              50.0,
              0.0,
              0.0,
              0.0,
              0.0,
              0.0,
              0.0,
              0.0,
              1.0,
              0.0,
              0.0,
              0.0,
              0.0,
              0.0,
              0.0,
              0.0
            ],
            "Scale": {
              "Min": 0.0,
              "Max": 100.0,
              "StepSize": 1.0,
              "DefaultValue": 50.0,
              "Labels": [
                "",
                "",
                "",
                "",
                ""
              ]
            },
            "PresentedOrderOfStimuli": [
              0
            ],
            "ElapsedTimeInSeconds": 7.633661099999999
          },
          {
            "TrialName": "2LS_15DEG_HP",
            "Ratings": [
              50.0,
              0.0,
              0.0,
              0.0,
              0.0,
              0.0,
              0.0,
              1.0,
              0.0,
              1.0,
              0.0,
              0.0,
              0.0,
              0.0,
              0.0,
              0.0
            ],
            "Scale": {
              "Min": 0.0,
              "Max": 100.0,
              "StepSize": 1.0,
              "DefaultValue": 50.0,
              "Labels": [
                "",
                "",
                "",
                "",
                ""
              ]
            },
            "PresentedOrderOfStimuli": [
              0
            ],
            "ElapsedTimeInSeconds": 8.1881776
          },
          {
            "TrialName": "2LS_30DEG_HP",
            "Ratings": [
              50.0,
              0.0,
              0.0,
              0.0,
              0.0,
              0.0,
              1.0,
              0.0,
              1.0,
              0.0,
              1.0,
              0.0,
              0.0,
              0.0,
              0.0,
              0.0
            ],
            "Scale": {
              "Min": 0.0,
              "Max": 100.0,
              "StepSize": 1.0,
              "DefaultValue": 50.0,
              "Labels": [
                "",
                "",
                "",
                "",
                ""
              ]
            },
            "PresentedOrderOfStimuli": [
              0
            ],
            "ElapsedTimeInSeconds": 9.659129099999999
          },
          {
            "TrialName": "2LS_45DEG_HP",
            "Ratings": [
              50.0,
              0.0,
              0.0,
              0.0,
              1.0,
              0.0,
              0.0,
              0.0,
              0.0,
              0.0,
              0.0,
              0.0,
              1.0,
              0.0,
              0.0,
              0.0
            ],
            "Scale": {
              "Min": 0.0,
              "Max": 100.0,
              "StepSize": 1.0,
              "DefaultValue": 50.0,
              "Labels": [
                "",
                "",
                "",
                "",
                ""
              ]
            },
            "PresentedOrderOfStimuli": [
              0
            ],
            "ElapsedTimeInSeconds": 8.008467899999999
          },
          {
            "TrialName": "2LS_60DEG_HP",
            "Ratings": [
              50.0,
              0.0,
              0.0,
              0.0,
              1.0,
              0.0,
              0.0,
              0.0,
              0.0,
              0.0,
              0.0,
              0.0,
              1.0,
              0.0,
              0.0,
              0.0
            ],
            "Scale": {
              "Min": 0.0,
              "Max": 100.0,
              "StepSize": 1.0,
              "DefaultValue": 50.0,
              "Labels": [
                "",
                "",
                "",
                "",
                ""
              ]
            },
            "PresentedOrderOfStimuli": [
              0
            ],
            "ElapsedTimeInSeconds": 16.7329194
          },
          {
            "TrialName": "2LS_90DEG_HP",
            "Ratings": [
              50.0,
              1.0,
              0.0,
              0.0,
              0.0,
              0.0,
              0.0,
              0.0,
              0.0,
              0.0,
              0.0,
              0.0,
              0.0,
              0.0,
              0.0,
              1.0
            ],
            "Scale": {
              "Min": 0.0,
              "Max": 100.0,
              "StepSize": 1.0,
              "DefaultValue": 50.0,
              "Labels": [
                "",
                "",
                "",
                "",
                ""
              ]
            },
            "PresentedOrderOfStimuli": [
              0
            ],
            "ElapsedTimeInSeconds": 9.671295899999999
          },
          {
            "TrialName": "3LS_15DEG_HP",
            "Ratings": [
              50.0,
              0.0,
              0.0,
              0.0,
              0.0,
              0.0,
              0.0,
              1.0,
              0.0,
              1.0,
              0.0,
              0.0,
              0.0,
              0.0,
              0.0,
              0.0
            ],
            "Scale": {
              "Min": 0.0,
              "Max": 100.0,
              "StepSize": 1.0,
              "DefaultValue": 50.0,
              "Labels": [
                "",
                "",
                "",
                "",
                ""
              ]
            },
            "PresentedOrderOfStimuli": [
              0
            ],
            "ElapsedTimeInSeconds": 17.1676026
          },
          {
            "TrialName": "3LS_30DEG_HP",
            "Ratings": [
              50.0,
              0.0,
              0.0,
              0.0,
              0.0,
              0.0,
              0.0,
              1.0,
              1.0,
              1.0,
              0.0,
              0.0,
              0.0,
              0.0,
              0.0,
              0.0
            ],
            "Scale": {
              "Min": 0.0,
              "Max": 100.0,
              "StepSize": 1.0,
              "DefaultValue": 50.0,
              "Labels": [
                "",
                "",
                "",
                "",
                ""
              ]
            },
            "PresentedOrderOfStimuli": [
              0
            ],
            "ElapsedTimeInSeconds": 12.0671451
          },
          {
            "TrialName": "3LS_45DEG_HP",
            "Ratings": [
              50.0,
              0.0,
              0.0,
              0.0,
              0.0,
              1.0,
              0.0,
              0.0,
              1.0,
              0.0,
              0.0,
              1.0,
              0.0,
              0.0,
              0.0,
              0.0
            ],
            "Scale": {
              "Min": 0.0,
              "Max": 100.0,
              "StepSize": 1.0,
              "DefaultValue": 50.0,
              "Labels": [
                "",
                "",
                "",
                "",
                ""
              ]
            },
            "PresentedOrderOfStimuli": [
              0
            ],
            "ElapsedTimeInSeconds": 12.0333505
          },
          {
            "TrialName": "3LS_60DEG_HP",
            "Ratings": [
              50.0,
              0.0,
              0.0,
              0.0,
              0.0,
              1.0,
              0.0,
              0.0,
              0.0,
              0.0,
              0.0,
              1.0,
              0.0,
              0.0,
              0.0,
              0.0
            ],
            "Scale": {
              "Min": 0.0,
              "Max": 100.0,
              "StepSize": 1.0,
              "DefaultValue": 50.0,
              "Labels": [
                "",
                "",
                "",
                "",
                ""
              ]
            },
            "PresentedOrderOfStimuli": [
              0
            ],
            "ElapsedTimeInSeconds": 15.0939851
          },
          {
            "TrialName": "3LS_90DEG_HP",
            "Ratings": [
              50.0,
              0.0,
              0.0,
              1.0,
              0.0,
              0.0,
              0.0,
              0.0,
              1.0,
              0.0,
              0.0,
              0.0,
              0.0,
              1.0,
              0.0,
              0.0
            ],
            "Scale": {
              "Min": 0.0,
              "Max": 100.0,
              "StepSize": 1.0,
              "DefaultValue": 50.0,
              "Labels": [
                "",
                "",
                "",
                "",
                ""
              ]
            },
            "PresentedOrderOfStimuli": [
              0
            ],
            "ElapsedTimeInSeconds": 6.7398199
          },
          {
            "TrialName": "13LS_90DEG_HP",
            "Ratings": [
              50.0,
              0.0,
              0.0,
              1.0,
              0.0,
              0.0,
              0.0,
              0.0,
              0.0,
              0.0,
              0.0,
              0.0,
              0.0,
              1.0,
              0.0,
              0.0
            ],
            "Scale": {
              "Min": 0.0,
              "Max": 100.0,
              "StepSize": 1.0,
              "DefaultValue": 50.0,
              "Labels": [
                "",
                "",
                "",
                "",
                ""
              ]
            },
            "PresentedOrderOfStimuli": [
              0
            ],
            "ElapsedTimeInSeconds": 10.0799127
          }
        ]
      }
    ]
  },
  "MushraAppVersion": "0.1.3"
}